universal_pathlib-0.3.5.dist-info/licenses/LICENSE
upath/__init__.py
upath/_chain.py
upath/_flavour.py
upath/_flavour_sources.py
upath/_info.py
upath/_protocol.py
upath/_stat.py
upath/_version.py
upath/core.py
upath/extensions.py
upath/py.typed
upath/registry.py
upath/implementations/__init__.py
upath/implementations/_experimental.py
upath/implementations/cached.py
upath/implementations/cloud.py
upath/implementations/data.py
upath/implementations/github.py
upath/implementations/hdfs.py
upath/implementations/http.py
upath/implementations/local.py
upath/implementations/memory.py
upath/implementations/sftp.py
upath/implementations/smb.py
upath/implementations/tar.py
upath/implementations/webdav.py
upath/implementations/zip.py
upath/types/__init__.py
upath/types/_abc.py
upath/types/_abc.pyi
upath/types/storage_options.py
universal_pathlib-0.3.5.dist-info/METADATA
universal_pathlib-0.3.5.dist-info/WHEEL
universal_pathlib-0.3.5.dist-info/top_level.txt
universal_pathlib-0.3.5.dist-info/RECORD
