Metadata-Version: 2.4
Name: universal_pathlib
Version: 0.3.5
Summary: pathlib api extended to use fsspec backends
Author-email: Andrew Fulton <andrewfulton9@gmail.com>
Maintainer: Norman Rzepka
Maintainer-email: Andreas Poehlmann <andreas@poehlmann.io>
License-Expression: MIT
Project-URL: Homepage, https://github.com/fsspec/universal_pathlib
Project-URL: Changelog, https://github.com/fsspec/universal_pathlib/blob/main/CHANGELOG.md
Keywords: filesystem-spec,pathlib
Classifier: Programming Language :: Python :: 3
Classifier: Programming Language :: Python :: 3.9
Classifier: Programming Language :: Python :: 3.10
Classifier: Programming Language :: Python :: 3.11
Classifier: Programming Language :: Python :: 3.12
Classifier: Programming Language :: Python :: 3.13
Classifier: Programming Language :: Python :: 3.14
Classifier: Development Status :: 4 - Beta
Requires-Python: >=3.9
License-File: LICENSE
Requires-Dist: fsspec>=2024.5.0
Requires-Dist: pathlib-abc<0.6.0,>=0.5.1
Provides-Extra: tests
Requires-Dist: pytest>=8; extra == "tests"
Requires-Dist: pytest-sugar>=0.9.7; extra == "tests"
Requires-Dist: pytest-cov>=4.1.0; extra == "tests"
Requires-Dist: pytest-mock>=3.12.0; extra == "tests"
Requires-Dist: pylint>=2.17.4; extra == "tests"
Requires-Dist: mypy>=1.10.0; extra == "tests"
Requires-Dist: pydantic>=2; extra == "tests"
Requires-Dist: pytest-mypy-plugins>=3.1.2; extra == "tests"
Requires-Dist: packaging; extra == "tests"
Provides-Extra: typechecking
Requires-Dist: mypy>=1.10.0; extra == "typechecking"
Requires-Dist: pytest-mypy-plugins>=3.1.2; extra == "typechecking"
Provides-Extra: dev
Requires-Dist: fsspec[adl,gcs,github,http,s3,smb,ssh]>=2024.5.0; extra == "dev"
Requires-Dist: s3fs>=2024.5.0; extra == "dev"
Requires-Dist: gcsfs>=2024.5.0; extra == "dev"
Requires-Dist: adlfs>=2024; extra == "dev"
Requires-Dist: huggingface_hub; extra == "dev"
Requires-Dist: webdav4[fsspec]; extra == "dev"
Requires-Dist: moto[s3,server]; extra == "dev"
Requires-Dist: wsgidav; extra == "dev"
Requires-Dist: cheroot; extra == "dev"
Requires-Dist: typing_extensions; python_version < "3.11" and extra == "dev"
Provides-Extra: dev-third-party
Requires-Dist: pydantic; extra == "dev-third-party"
Requires-Dist: pydantic-settings; extra == "dev-third-party"
Dynamic: license-file
